pmg/__init__.py
pmg/base36.py
pmg/db.py
pmg/latex.py
pmg/system.py
pmg/typecast.py
pmg/sqlite/__init__.py
pmg/sqlite/factories.py
pmg/sqlite/queues.py
pmg-1.0.6.dist-info/licenses/LICENSE
pmg-1.0.6.dist-info/METADATA
pmg-1.0.6.dist-info/WHEEL
pmg-1.0.6.dist-info/top_level.txt
pmg-1.0.6.dist-info/RECORD
