Metadata-Version: 2.4
Name: pmg
Version: 1.0.6
Summary: A toolbox full of handy little helper functions and utilities.
Author-email: Preston Meyer Group <dev@pmgroup.ch>
License-Expression: MIT
Keywords: tools,utils
Classifier: Development Status :: 5 - Production/Stable
Classifier: Programming Language :: Python :: 3
Classifier: Operating System :: OS Independent
Classifier: Intended Audience :: Developers
Requires-Python: >=3.9
License-File: LICENSE
Provides-Extra: test
Requires-Dist: pytest; extra == "test"
Requires-Dist: hypothesis; extra == "test"
Dynamic: license-file
